{
  "total_seconds": 159786.557,
  "total_hours": "44.39",
  "languages": [
    {
      "name": "TypeScript",
      "total_seconds": 70214.596,
      "percent": 42.44
    },
    {
      "name": "Dart",
      "total_seconds": 51831.658,
      "percent": 31.33
    },
    {
      "name": "Bash",
      "total_seconds": 9564.785,
      "percent": 5.78
    },
    {
      "name": "Markdown",
      "total_seconds": 7053.994,
      "percent": 4.26
    },
    {
      "name": "SQL",
      "total_seconds": 6907.866,
      "percent": 4.18
    }
  ],
  "last_updated": "11/12/2025 01:11",
  "range": "last_30_days"
}