{
  "total_seconds": 151382.040305,
  "total_hours": "42.05",
  "languages": [
    {
      "name": "Dart",
      "total_seconds": 84402.833,
      "percent": 55
    },
    {
      "name": "TypeScript",
      "total_seconds": 30890.706042,
      "percent": 20.13
    },
    {
      "name": "YAML",
      "total_seconds": 8781.029,
      "percent": 5.72
    },
    {
      "name": "Markdown",
      "total_seconds": 7930.363419,
      "percent": 5.17
    },
    {
      "name": "Bash",
      "total_seconds": 6204.138083,
      "percent": 4.04
    }
  ],
  "last_updated": "21/11/2025 01:06",
  "range": "last_30_days"
}