{
  "total_seconds": 331614.002,
  "total_hours": "92.12",
  "languages": [
    {
      "name": "Dart",
      "total_seconds": 222193.38,
      "percent": 63.94
    },
    {
      "name": "TypeScript",
      "total_seconds": 55386.299,
      "percent": 15.94
    },
    {
      "name": "YAML",
      "total_seconds": 16785.047,
      "percent": 4.83
    },
    {
      "name": "Other",
      "total_seconds": 15911.358,
      "percent": 4.58
    },
    {
      "name": "Markdown",
      "total_seconds": 9815.948,
      "percent": 2.82
    }
  ],
  "last_updated": "22/06/2026 03:32",
  "range": "last_30_days"
}